<annotation>
	<folder>images</folder>
	<filename>Blattfeder_original_20180306_091147.jpg_783a406e-3b3e-4bdf-afbb-c92483d6392d.jpg</filename>
	<path>C:\Users\IBM_ADMIN\Documents\Programming\python\Custom-Object-Detection\images\Blattfeder_original_20180306_091147.jpg_783a406e-3b3e-4bdf-afbb-c92483d6392d.jpg</path>
	<source>
		<database>Unknown</database>
	</source>
	<size>
		<width>640</width>
		<height>480</height>
		<depth>3</depth>
	</size>
	<segmented>0</segmented>
	<object>
		<name>blattfederww</name>
		<pose>Unspecified</pose>
		<truncated>0</truncated>
		<difficult>0</difficult>
		<bndbox>
			<xmin>262</xmin>
			<ymin>181</ymin>
			<xmax>611</xmax>
			<ymax>286</ymax>
		</bndbox>
	</object>
</annotation>
